orji/__init__.py
orji/app.py
orji/calculation.py
orji/exceptions.py
orji/ical.py
orji/insert.py
orji/loader.py
orji/lookup.py
orji/note.py
orji/output.py
orji/remove.py
orji/run.py
orji/tempdir.py
orji/template.py
orji/vcf.py
orji-4.5.0.dist-info/LICENSE
orji-4.5.0.dist-info/METADATA
orji-4.5.0.dist-info/WHEEL
orji-4.5.0.dist-info/entry_points.txt
orji-4.5.0.dist-info/top_level.txt
orji-4.5.0.dist-info/RECORD
