Metadata-Version: 2.1
Name: orji
Version: 4.5.0
Summary: Org mode to jinja2 templating.
Author-email: Colm O'Connor <colm.oconnor.github@gmail.com>
License: MIT
Project-URL: homepage, https://hitchdev.com/orji
Project-URL: documentation, https://hitchdev.com/orji/using
Project-URL: repository, https://github.com/crdoconnor/orji
Project-URL: changelog, https://hitchdev.com/orji/changelog
Keywords: orgmode,markdown,latex,jinja2
Classifier: Programming Language :: Python :: 3
Classifier: License :: OSI Approved :: MIT License
Classifier: Topic :: Text Processing :: Markup
Classifier: Topic :: Software Development :: Libraries
Classifier: Natural Language :: English
Requires-Python: >=3.7.0
License-File: LICENSE
Requires-Dist: orgmunge >=0.2.0
Requires-Dist: jinja2 >=3.1.2
Requires-Dist: click >=8.1.3
Requires-Dist: python-slugify >=7.0.0
Requires-Dist: icalendar >=5.0.11
Requires-Dist: vobject >=0.9.7
